mtweepy/__init__.py
mtweepy-1.0.2.dist-info/LICENSE
mtweepy-1.0.2.dist-info/METADATA
mtweepy-1.0.2.dist-info/WHEEL
mtweepy-1.0.2.dist-info/top_level.txt
mtweepy-1.0.2.dist-info/RECORD
