Metadata-Version: 2.1
Name: mtweepy
Version: 1.0.2
Summary: Provides a basic package structure
Home-page: https://github.com/Souvic/mtweepy.git
Author: Souvic Chakraborty
Author-email: chakra.souvic@gmail.com
License: UNKNOWN
Project-URL: Bug Tracker, https://github.com/Souvic/mtweepy.git/issues
Platform: UNKNOWN
Classifier: Programming Language :: Python :: 3
Classifier: License :: OSI Approved :: MIT License
Classifier: Operating System :: OS Independent
Requires-Python: >=3.6
License-File: LICENSE
Requires-Dist: requests (>=2.25.1)
Requires-Dist: requests-oauthlib (>=1.3.0)
Requires-Dist: tweepy (>=3.10.0)
